ghnotifier/__init__.py
ghnotifier/config.ini
ghnotifier/config.py
ghnotifier/gh.png
ghnotifier/indicator.py
ghnotifier/menu.py
ghnotifier/notifier.py
ghnotifier/settings.py
ghnotifier-0.1.8.data/scripts/ghnotifier
ghnotifier-0.1.8.dist-info/LICENSE
ghnotifier-0.1.8.dist-info/METADATA
ghnotifier-0.1.8.dist-info/WHEEL
ghnotifier-0.1.8.dist-info/top_level.txt
ghnotifier-0.1.8.dist-info/RECORD
