Metadata-Version: 2.1
Name: ghnotifier
Version: 0.1.8
Summary: Github notifications.
Home-page: http://github.com/kunicmarko20/ghnotifier
Author: Marko Kunic
Author-email: kunicmarko20@gmail.com
License: MIT
Platform: UNKNOWN
Requires-Dist: configparser
Requires-Dist: requests
